silence_remover/__init__.py
silence_remover/silence_remover.py
silence_remover/filter_generator/__init__.py
silence_remover/filter_generator/filter_generator.py
silence_remover/media_editor/__init__.py
silence_remover/media_editor/media_editor.py
silence_remover/silence_detector/__init__.py
silence_remover/silence_detector/interval_parser.py
silence_remover/silence_detector/silence_detector.py
silence_remover-1.0.0.dist-info/METADATA
silence_remover-1.0.0.dist-info/WHEEL
silence_remover-1.0.0.dist-info/top_level.txt
silence_remover-1.0.0.dist-info/RECORD
