Metadata-Version: 2.1
Name: silence-remover
Version: 1.0.0
Summary: Remove silent parts from any media file
Home-page: https://github.com/lagmoellertim/silence-remover
Author: Tim-Luca Lagmöller
Author-email: hello@lagmoellertim.de
License: MIT License
Platform: UNKNOWN
Classifier: Programming Language :: Python :: 3
Classifier: License :: OSI Approved :: MIT License
Classifier: Operating System :: OS Independent
